opensr_test/__init__.py
opensr_test/config.py
opensr_test/correctness.py
opensr_test/dataset.py
opensr_test/distance.py
opensr_test/main.py
opensr_test/plot.py
opensr_test/spatial.py
opensr_test/utils.py
opensr_test-1.3.3.dist-info/LICENSE
opensr_test-1.3.3.dist-info/METADATA
opensr_test-1.3.3.dist-info/WHEEL
opensr_test-1.3.3.dist-info/RECORD
