Metadata-Version: 2.1
Name: opensr_test
Version: 1.3.3
Summary: A comprehensive benchmark for real-world Sentinel-2 imagery super-resolution
Home-page: https://github.com/csaybar/opensr-test
Author: Cesar Aybar
Author-email: cesar.aybar@uv.es
Requires-Python: >=3.10,<4.0
Classifier: Programming Language :: Python :: 3
Classifier: Programming Language :: Python :: 3.10
Classifier: Programming Language :: Python :: 3.11
Classifier: Programming Language :: Python :: 3.12
Requires-Dist: kornia (>=0.7.2)
Requires-Dist: lpips[perceptual] (>=0.1.4)
Requires-Dist: matplotlib (>=3.7.0)
Requires-Dist: mpltern (>=1.0.4)
Requires-Dist: numpy (>=1.25.2)
Requires-Dist: open-clip-torch[perceptual] (>=2.24.0)
Requires-Dist: openai-clip[perceptual] (>=1.0.1)
Requires-Dist: opencv-python (>=4.8.0.0)
Requires-Dist: pydantic (>=2.7.1)
Requires-Dist: requests (>=2.25.0)
Requires-Dist: satalign (>=0.1.3)
Requires-Dist: scikit-image (>=0.19.0)
Requires-Dist: torchvision (>=0.17.0)
Project-URL: Documentation, https://csaybar.github.io/opensr-test/
Project-URL: Repository, https://github.com/csaybar/opensr-test
